pyqt_realtime_log_widget/__init__.py
pyqt_realtime_log_widget/example.py
pyqt_realtime_log_widget/logWidget.py
pyqt_realtime_log_widget-0.0.11.dist-info/LICENSE
pyqt_realtime_log_widget-0.0.11.dist-info/METADATA
pyqt_realtime_log_widget-0.0.11.dist-info/WHEEL
pyqt_realtime_log_widget-0.0.11.dist-info/top_level.txt
pyqt_realtime_log_widget-0.0.11.dist-info/RECORD
