Metadata-Version: 2.1
Name: pyqt-realtime-log-widget
Version: 0.0.11
Summary: Display log in real time with PyQt
Home-page: https://github.com/yjg30737/pyqt-realtime-log-widget.git
Author: Jung Gyu Yoon
Author-email: yjg30737@gmail.com
License: MIT
License-File: LICENSE
Requires-Dist: PyQt5
Requires-Dist: psutil
